{"text_titre_pour_les_formations":{"type":"text","data":"Nos formations","wysiwyg":false},"text_description_des_formations":{"type":"text","data":"En compl\u00e9ment de notre offre produits, nous vous proposons une large gamme de formations. Dans une d\u00e9marche globale d\u2019am\u00e9lioration de la qualit\u00e9 de votre travail, nous analyserons avec vous vos besoins et nous adapterons nos programmes. Consultez-nous !\r\n","wysiwyg":false},"text_titre_pour_les_specificite_de_eo_securite":{"type":"text","data":"Les sp\u00e9cificit\u00e9s EO S\u00e9curit\u00e9","wysiwyg":false},"text_premiere_specificite_eo_securite":{"type":"text","data":"Stages acc\u00e9l\u00e9r\u00e9s et efficaces","wysiwyg":false},"text_deuxieme_specificite_eo_securite":{"type":"text","data":"Non reconnu par les institutions","wysiwyg":false},"text_troisieme_specificite_eo_securite":{"type":"text","data":"Stages de qualit\u00e9 r\u00e9alis\u00e9s par des experts","wysiwyg":false}}